setup.py
pydisbn/Binomialdistribution.py
pydisbn/Gaussiandistribution.py
pydisbn/Generaldistribution.py
pydisbn/__init__.py
pydisbn.egg-info/PKG-INFO
pydisbn.egg-info/SOURCES.txt
pydisbn.egg-info/dependency_links.txt
pydisbn.egg-info/not-zip-safe
pydisbn.egg-info/top_level.txt